feos_torch-0.1.0.dist-info/METADATA
feos_torch-0.1.0.dist-info/WHEEL
feos_torch-0.1.0.dist-info/license_files/LICENSE-APACHE
feos_torch-0.1.0.dist-info/license_files/LICENSE-MIT
feos_torch/dual.py
feos_torch/dual_torch.py
feos_torch/gc_pcsaft.py
feos_torch/pcsaft_mix.py
feos_torch/pcsaft_pure.py
feos_torch/__init__.py
feos_torch/feos_torch.pyd
feos_torch-0.1.0.dist-info/RECORD
