Metadata-Version: 2.3
Name: feos-torch
Version: 0.1.0
Requires-Dist: torch
Requires-Dist: numpy
Requires-Dist: si-units
License-File: LICENSE-APACHE
License-File: LICENSE-MIT
Summary: FeOs-torch - Automatic differentiation of phase equilibria.
Keywords: physics,thermodynamics,equations_of_state,phase_equilibria
Author: Philipp Rehner <prehner@ethz.ch>
Author-email: Philipp Rehner <prehner@ethz.ch>
License: MIT OR Apache-2.0
Project-URL: Source Code, https://github.com/feos-org/feos-torch
